gopyadapter/__init__.py
gopyadapter/core.py
gopyadapter-1.0.1.dist-info/LICENSE
gopyadapter-1.0.1.dist-info/METADATA
gopyadapter-1.0.1.dist-info/WHEEL
gopyadapter-1.0.1.dist-info/RECORD
