Metadata-Version: 2.3
Name: gopyadapter
Version: 1.0.1
Summary: Allows easy management of a python process and calling of python from go
License: MIT
Author: Joss Peters
Author-email: jptrs93@gmail.com
Requires-Python: >=3.9,<4.0
Classifier: License :: OSI Approved :: MIT License
Classifier: Programming Language :: Python :: 3
Classifier: Programming Language :: Python :: 3.9
Classifier: Programming Language :: Python :: 3.10
Classifier: Programming Language :: Python :: 3.11
Classifier: Programming Language :: Python :: 3.12
Classifier: Programming Language :: Python :: 3.13
Requires-Dist: msgpack (>=1.1.0,<2.0.0)
Requires-Dist: numpy (>=1.20,<2.0)
Project-URL: Repository, https://github.com/jptrs93/gopy/gopyadapter
